mlassist/__init__.py
mlassist/linregressor.py
mlassist/mlhelper.py
mlassist-0.0.3.dist-info/LICENSE.txt
mlassist-0.0.3.dist-info/METADATA
mlassist-0.0.3.dist-info/WHEEL
mlassist-0.0.3.dist-info/top_level.txt
mlassist-0.0.3.dist-info/RECORD
