Metadata-Version: 2.1
Name: mlassist
Version: 0.0.3
Summary: Helping Package for creating Machine Learning models
Home-page: UNKNOWN
Author: Debanjan Chowdhury
License: UNKNOWN
Platform: UNKNOWN
Classifier: Programming Language :: Python :: 3
Classifier: License :: OSI Approved :: MIT License
Classifier: Operating System :: OS Independent
Requires-Python: >=3.6
License-File: LICENSE.txt
Requires-Dist: pandas
Requires-Dist: sklearn
Requires-Dist: pandas-profiling
Requires-Dist: statsmodels
